ten8t/.DS_Store
ten8t/__init__.py
ten8t/cli/__init__.py
ten8t/cli/apple_touch_icon.png
ten8t/cli/result.csv
ten8t/cli/result.md
ten8t/cli/result.xlsx
ten8t/cli/ten8t_api.py
ten8t/cli/ten8t_cli.py
ten8t/examples/__init__.py
ten8t/examples/file_system/__init__.py
ten8t/examples/file_system/check_file_system.py
ten8t/examples/file_system/folder1/file1.txt
ten8t/examples/file_system/folder1/file2.txt
ten8t/examples/file_system/folder2/file1.txt
ten8t/examples/file_system/folder2/file2.txt
ten8t/examples/my_package/__init__.py
ten8t/examples/my_package/check_module1.py
ten8t/examples/my_package/check_module2.py
ten8t/progress/__init__.py
ten8t/progress/_base.py
ten8t/progress/concrete/__init__.py
ten8t/progress/concrete/_debug.py
ten8t/progress/concrete/_log.py
ten8t/progress/concrete/_multi.py
ten8t/progress/concrete/_no.py
ten8t/rc/__init__.py
ten8t/rc/_base.py
ten8t/rc/_factory.py
ten8t/rc/concrete/__init__.py
ten8t/rc/concrete/_ini.py
ten8t/rc/concrete/_json.py
ten8t/rc/concrete/_toml.py
ten8t/rc/concrete/_xml.py
ten8t/render/__init__.py
ten8t/render/_base.py
ten8t/render/_factory.py
ten8t/render/_markup.py
ten8t/render/_protocol.py
ten8t/render/concrete/__init__.py
ten8t/render/concrete/github_markdown.py
ten8t/render/concrete/html.py
ten8t/render/concrete/markdown.py
ten8t/render/concrete/rich.py
ten8t/render/concrete/streamlit.py
ten8t/render/concrete/text.py
ten8t/rich_ten8t/rich_demo.py
ten8t/rule_fs.py
ten8t/rule_ndf.py
ten8t/rule_pathlib.py
ten8t/rule_pdf.py
ten8t/rule_ping.py
ten8t/rule_sqlachemy.py
ten8t/rule_webapi.py
ten8t/rule_xlsx.py
ten8t/score/__init__.py
ten8t/score/_base.py
ten8t/score/_factory.py
ten8t/score/_protocol.py
ten8t/score/_util.py
ten8t/score/concrete/__init__.py
ten8t/score/concrete/_binary_fail.py
ten8t/score/concrete/_binary_pass.py
ten8t/score/concrete/_by_result.py
ten8t/score/concrete/_function_binary.py
ten8t/score/concrete/_function_mean.py
ten8t/serialize/__init__.py
ten8t/serialize/_base.py
ten8t/serialize/_config.py
ten8t-0.0.22.dist-info/LICENSE
ten8t-0.0.22.dist-info/METADATA
ten8t-0.0.22.dist-info/WHEEL
ten8t-0.0.22.dist-info/RECORD
