Metadata-Version: 2.3
Name: ten8t
Version: 0.0.22
Summary: Tool for generic infrastructure linting.
License: MIT
Author: Chuck Bass
Author-email: chuck@arcocad.net
Maintainer: Chuck Bass
Maintainer-email: chuck@arcocad.net
Requires-Python: >=3.10
Classifier: Development Status :: 3 - Alpha
Classifier: Intended Audience :: Developers
Classifier: Programming Language :: Python :: 3.10
Classifier: Programming Language :: Python :: 3.11
Classifier: Programming Language :: Python :: 3.12
Classifier: Programming Language :: Python :: 3.13
Requires-Dist: anyio (>=4.9.0,<4.10.0)
Requires-Dist: attrs (>=25.3.0,<25.4.0)
Requires-Dist: click
Requires-Dist: coverage (>=7.7.1,<7.8.0)
Requires-Dist: cryptography (>=44.0.2)
Requires-Dist: fastapi (>=0.115.12,<0.116.0)
Requires-Dist: filelock (>=3.18.0,<3.19.0)
Requires-Dist: fs
Requires-Dist: gitdb2 (>=3.0.3,<3.1.0)
Requires-Dist: humanize (>=4.12.0,<4.13.0)
Requires-Dist: iniconfig (>=2.1.0,<2.2.0)
Requires-Dist: jinja2 (>=3.1.6,<3.2.0)
Requires-Dist: mando (>=0.8.2,<0.9.0)
Requires-Dist: narwhals (>=1.30.0,<1.31.0)
Requires-Dist: nh3 (>=0.2.21,<0.3.0)
Requires-Dist: numpy (>=2.2.4,<2.3.0)
Requires-Dist: openpyxl
Requires-Dist: orjson (>=3.10.16,<3.11.0)
Requires-Dist: pandas-stubs (>=2.2.3.250308,<2.3.0.0)
Requires-Dist: pydantic (>=2.10.0,<2.11.0)
Requires-Dist: pypdf (>=5.4.0,<5.5.0)
Requires-Dist: requests
Requires-Dist: rich
Requires-Dist: smmap (>=5.0.0,<5.1.0)
Requires-Dist: sqlalchemy (>=2.0.39,<2.1.0)
Requires-Dist: starlette (>=0.46.0,<0.47.0)
Requires-Dist: streamlit (>=1.43.0,<1.44.0)
Requires-Dist: textual (==2.0.0)
Requires-Dist: toml
Requires-Dist: typer (>=0.15.2,<0.16.0)
Requires-Dist: types-requests (>=2.32.0.20250306,<2.33.0.0)
Requires-Dist: tzlocal (>=5.3.1,<5.4.0)
Requires-Dist: uv (>=0.6.9,<0.7.0)
Requires-Dist: uvicorn
Requires-Dist: virtualenv (>=20.29.3,<20.30.0)
Requires-Dist: websockets (>=15.0.1,<15.1.0)
Project-URL: Homepage, https://github.com/hucker233/ten8t
